{
    "InternalName": "MercatorRotateParts",
    "ClassNameSMG1": "MercatorRotateParts",
    "ClassNameSMG2": "MercatorRotateParts",
    "Name": "Generic Rotating Mercator Map Object [Unused]",
    "Notes": "A rotating object that uses Mercator projection for placement. It retrieves a proper model using ShapeModelNo, however, no more models exist for this object.",
    "Category": "deprecated",
    "AreaShape": "Any",
    "ListSMG1": "MapPartsInfo",
    "ListSMG2": "MapPartsInfo",
    "File": "Map",
    "Games": 1,
    "Progress": 2,
    "IsUnused": true,
    "IsLeftover": false
}