{
    "InternalName": "SwitchBox",
    "ClassNameSMG1": "SwitchBox",
    "ClassNameSMG2": "SwitchBox",
    "Name": "Red \"?\" Block",
    "Notes": "An unusual looking red and pink \"?\" block.\n\nBehaves like a regular \"?\" block but does not drop anything, instead it fires the events linked to it's SW_DEAD",
    "Category": "levelfeature",
    "AreaShape": "Any",
    "ListSMG1": "ObjInfo",
    "ListSMG2": "ObjInfo",
    "File": "Map",
    "Games": 1,
    "Progress": 0,
    "IsUnused": true,
    "IsLeftover": false
}