{
    "InternalName": "TicoAstro",
    "ClassNameSMG1": "TicoAstro",
    "ClassNameSMG2": "TicoAstro",
    "Name": "Luma [Comet Observatory]",
    "Notes": "A special Luma object for the Comet Observatory. Only used by the 3 Green Lumas surrounding the Green Launch Star to the Planet of Trials.",
    "Category": "npc",
    "AreaShape": "Any",
    "ListSMG1": "ObjInfo",
    "ListSMG2": "ObjInfo",
    "File": "Map",
    "Games": 1,
    "Progress": 1,
    "IsUnused": false,
    "IsLeftover": false
}