{
    "InternalName": "WanwanObstacleFloaterB",
    "ClassName": "SimpleFloaterObj",
    "Name": "Chompworks: Double Sinking Platform",
    "Notes": "Two side-by-side blue platforms that sink together when Mario/Luigi stand on them. Used on the starting planet of Chompworks Galaxy.\n\n[MapPart Arguments]\nMoveConditionType: Distance - How far it sinks (a negative value to make the object rising up will glitch, turning the object over instead will work)\nRotateSpeed: Sinking Speed - How fast it sinks\nRotateAngle: Return Speed - How fast it comes back to it's initial height",
    "Category": "unknown",
    "Games": 2,
    "Progress": 1,
    "IsUnused": false,
    "IsLeftover": false
}