{
    "InternalName": "BigRepeatWarpLift",
    "Notes": "A platform that moves on a path and teleports back to the beginning after it has reached the end. Lastly, it also supports an optional Bloom model.",
    "Games": 2,
    "Progress": 2,
    "Parameters": {
        "SW_APPEAR": {
            "Games": 2,
            "Needed": false,
            "Exclusives": []
        },
        "SW_A": {
            "Games": 2,
            "Needed": false,
            "Description": "Makes the object move while the switch is active.",
            "Exclusives": []
        },
        "SW_B": {
            "Games": 2,
            "Needed": false,
            "Description": "Makes the object stop while the switch is not active.",
            "Exclusives": []
        },
        "SW_AWAKE": {
            "Games": 2,
            "Needed": false,
            "Exclusives": []
        },
        "Rail": {
            "Games": 2,
            "Needed": true,
            "Description": "The path that the platform moves on. Used by MapPartsRailMover.",
            "Exclusives": []
        },
        "ClippingGroup": {
            "Games": 2,
            "Needed": false,
            "Exclusives": []
        },
        "DemoCast": {
            "Games": 2,
            "Needed": false,
            "Description": "The object takes part in the cutscene.",
            "Exclusives": []
        },
        "MapPartsRailMover": {
            "Games": 2,
            "Needed": false,
            "Exclusives": []
        },
        "BaseMtxFollowTarget": {
            "Games": 2,
            "Needed": false,
            "Exclusives": []
        }
    }
}