{
    "InternalName": "ExterminationSwitch",
    "Notes": "A controller that activates a switch once all linked and compatible objects have been killed. Individual objects can be linked to this object by setting their GeneratorId to this object's l_id. ExterminationPowerStar spawns a Power Star after killing all objects. It also uses a counter layout to keep track of killed objects.",
    "Games": 2,
    "Progress": 2,
    "Parameters": {
        "Obj_arg0": {
            "Name": "Power Star ID",
            "Type": "Integer",
            "Games": 2,
            "Needed": false,
            "Description": "The Power Star's ID that should be spawned. If set to -1, it will automatically detect the proper Power Star to be spawned.",
            "Values": [],
            "Exclusives": [
                "ExterminationPowerStar"
            ]
        },
        "Obj_arg1": {
            "Name": "Activation Delay",
            "Type": "Integer",
            "Games": 2,
            "Needed": false,
            "Description": "The delay until the switch gets activated. Default is 0.",
            "Values": [],
            "Exclusives": [
                "ExterminationSwitch"
            ]
        },
        "Obj_arg2": {
            "Name": "Hide Counter?",
            "Type": "Boolean",
            "Games": 2,
            "Needed": false,
            "Description": "If set, the counter layout will be hidden.",
            "Values": [],
            "Exclusives": [
                "ExterminationPowerStar"
            ]
        },
        "SW_APPEAR": {
            "Games": 2,
            "Needed": false,
            "Description": "The object will appear when this switch is activated.",
            "Exclusives": []
        },
        "SW_A": {
            "Games": 2,
            "Needed": false,
            "Description": "Activated after killing all linked objects.",
            "Exclusives": []
        },
        "SW_AWAKE": {
            "Games": 2,
            "Needed": false,
            "Description": "The object will become visible and resume movement hwhen this switch is activated.",
            "Exclusives": []
        },
        "AppearPowerStar": {
            "Games": 2,
            "Needed": true,
            "Description": "Appears after killing all linked objects.",
            "Exclusives": [
                "ExterminationPowerStar"
            ]
        }
    }
}