{
    "InternalName": "Trapeze",
    "Notes": "A swing that the player can swing across by grabbing onto it. The player can jump off  it at any given time. scale_y specifies the length of the swing.",
    "Games": 3,
    "Progress": 2,
    "Parameters": {
        "Obj_arg0": {
            "Name": "Additional Shadow Length",
            "Type": "Float",
            "Games": 2,
            "Needed": false,
            "Description": "How much to add to the shadow's length. Default is 1000.",
            "Values": [],
            "Exclusives": []
        },
        "Obj_arg1": {
            "Name": "Shadow Cut Length",
            "Type": "Float",
            "Games": 2,
            "Needed": false,
            "Description": "How much to subtract from the shadow's length. Default is 0.",
            "Values": [],
            "Exclusives": []
        },
        "Camera": {
            "Games": 3,
            "Needed": false,
            "Description": "Used when climbing on and swinging on the swing.",
            "Exclusives": []
        },
        "DemoSimpleCast": {
            "Games": 3,
            "Description": "This object will not pause its movement during cutscenes, NPC conversations, etc.",
            "Exclusives": []
        }
    }
}