{
    "InternalName": "HanachanRunaway",
    "Notes": "A variant of a Wiggler intended to be used on tube slides. It needs to be connected to a proper TubeSlider instance using GeneratorId in order to be created. Its Obj_args specify how it gets positioned on the slide. Unlike its normal variants, it cannot be defeated. However, it can be frozen by the Orange Luma.",
    "Games": 2,
    "Progress": 2,
    "Parameters": {
        "Obj_arg0": {
            "Name": "Forwards Speed",
            "Type": "Integer",
            "Games": 2,
            "Needed": false,
            "Description": "How fast it moves along the TubeSlider's path. The actual speed value needs to be multiplied by 10. Default is 100.",
            "Values": [],
            "Exclusives": []
        },
        "Obj_arg1": {
            "Name": "Sidewards Speed",
            "Type": "Integer",
            "Games": 2,
            "Needed": false,
            "Description": "How fast it revolves around the TubeSlider's path. The actual speed value needs to be multiplied by 10. Default is 20.",
            "Values": [],
            "Exclusives": []
        },
        "Obj_arg2": {
            "Name": "Number of Body Parts",
            "Type": "Integer",
            "Games": 2,
            "Needed": false,
            "Description": "How many body parts it consists of. Minimum is 1, default is 5.",
            "Values": [],
            "Exclusives": []
        },
        "Obj_arg3": {
            "Name": "Is Angry?",
            "Type": "Boolean",
            "Games": 2,
            "Needed": false,
            "Description": "If set, it will turn red and move around more aggressively.",
            "Values": [],
            "Exclusives": []
        },
        "Obj_arg5": {
            "Name": "Initial Angle",
            "Type": "Float",
            "Games": 2,
            "Needed": false,
            "Description": "The angle around the tube slide at which the object gets positioned initially.",
            "Values": [],
            "Exclusives": []
        },
        "SW_A": {
            "Games": 2,
            "Needed": false,
            "Description": "If used, it will remain inactive until this switch gets activated.",
            "Values": [],
            "Exclusives": []
        },
        "ClippingGroup": {
            "Games": 2,
            "Description": "Objects in this group are always clipped together.",
            "Values": [],
            "Exclusives": []
        }
    }
}