{
    "InternalName": "RaceRail",
    "Name": "RaceRail",
    "Notes": "Lays out the rough layout of a race minigame.",
    "Games": 3,
    "Progress": 2,
    "Parameters": {
        "Path_arg0": {
            "Name": "Race ID",
            "Type": "Integer",
            "Games": 2,
            "Needed": false,
            "Description": "The race's internal ID. Default is 0.",
            "Values": [
                {
                    "Value": "0",
                    "Notes": "Sea Slide (SMG1) / Wild Glide (SMG2)"
                },
                {
                    "Value": "1",
                    "Notes": "Ghostly (SMG2) / Fleet Glide (SMG2)"
                },
                {
                    "Value": "2",
                    "Notes": "Boo's Boneyard (SMG1)"
                },
                {
                    "Value": "3",
                    "Notes": "Loopdeeloop (SMG1)"
                },
                {
                    "Value": "4",
                    "Notes": "Loopdeeswoop (SMG1)"
                },
                {
                    "Value": "5",
                    "Notes": ""
                }
            ],
            "Exclusives": []
        },
        "Path_arg7": {
            "Name": "Goal Radius",
            "Type": "Float",
            "Games": 3,
            "Needed": false,
            "Description": "The valid goal point range. Default is 650.",
            "Values": [],
            "Exclusives": []
        },
        "Point_arg0": {
            "Name": "Requires Pass?",
            "Type": "Boolean",
            "Games": 1,
            "Needed": false,
            "Description": "If set, this point needs to be passed by the player.",
            "Values": [],
            "Exclusives": []
        },
        "SW_APPEAR": {
            "Games": 3,
            "Needed": false,
            "Description": "Appears when this switch is activated.",
            "Exclusives": []
        },
        "Rail": {
            "Games": 3,
            "Needed": true,
            "Description": "Lays out the rough course of the race.",
            "Exclusives": []
        },
        "NamePos": {
            "Games": 2,
            "Needed": true,
            "Description": "Additional placements that can be freely placed.",
            "Values": [
                {
                    "Value": "レース開始時マリオ位置",
                    "Notes": "Player's position at the race's start"
                }
            ],
            "Exclusives": []
        },
        "Camera": {
            "Games": 3,
            "Needed": false,
            "Description": "Used when the race stars.",
            "Values": [],
            "Exclusives": []
        }
    }
}