{
    "InternalName": "Sky",
    "Name": "Sky",
    "Notes": "A decorative background model that is meant to be placed around entire galaxies. It follows the camera's position, so it's not possible for the player to reach the end of the model, unlike atmosphere objects.",
    "Games": 3,
    "Progress": 2,
    "Parameters": {
        "Obj_arg0": {
            "Name": "Mirror Reflection Type",
            "Type": "Integer",
            "Games": 3,
            "Needed": false,
            "Description": "Specifies whether to use a reflection model or not.",
            "Values": [
                {
                    "Value": "-1",
                    "Notes": "Don't use reflection model"
                },
                {
                    "Value": "0",
                    "Notes": "Use reflection model"
                }
            ],
            "Exclusives": []
        },
        "SW_APPEAR": {
            "Games": 3,
            "Needed": false,
            "Description": "The object will appear when this switch is activated.",
            "Exclusives": []
        },
        "SW_A": {
            "Games": 3,
            "Needed": false,
            "Description": "Plays the \"Change\" animation if activated.",
            "Exclusives": []
        },
        "SW_B": {
            "Games": 3,
            "Needed": false,
            "Description": "If used and activated, the sky model will disappear and the SpaceInner model will be used instead. If the switch gets deactivated again, SpaceInner disappears and the original sky model will reappear.",
            "Exclusives": [
                "SummerSky"
            ]
        },
        "SW_AWAKE": {
            "Games": 2,
            "Description": "Enables rendering and resumes updates when this switch is active.",
            "Exclusives": []
        },
        "DemoSimpleCast": {
            "Games": 3,
            "Description": "Continues movement during cutscenes, NPC conversations, etc.",
            "Exclusives": []
        }
    }
}